__init__.py
fixess.py
fixess-0.0.6.dist-info/LICENSE
fixess-0.0.6.dist-info/METADATA
fixess-0.0.6.dist-info/WHEEL
fixess-0.0.6.dist-info/top_level.txt
fixess-0.0.6.dist-info/RECORD
