Metadata-Version: 2.1
Name: fixess
Version: 0.0.6
Summary: Fixess cloud AI database client for Python
Project-URL: Bug Tracker, https://github.com/fixess-github/fixess-python
Project-URL: Source, https://github.com/fixess-github/fixess-python
Keywords: cloud AI,database,cloud database,database client,AI,model training,big data,deep learning,machine learning
License-File: LICENSE
